modularitypruning/__init__.py
modularitypruning/champ_utilities.py
modularitypruning/leiden_utilities.py
modularitypruning/louvain_utilities.py
modularitypruning/parameter_estimation.py
modularitypruning/parameter_estimation_utilities.py
modularitypruning/partition_utilities.py
modularitypruning/plotting.py
modularitypruning/progress.py
modularitypruning-1.5.0.dist-info/licenses/LICENSE
modularitypruning-1.5.0.dist-info/METADATA
modularitypruning-1.5.0.dist-info/WHEEL
modularitypruning-1.5.0.dist-info/top_level.txt
modularitypruning-1.5.0.dist-info/RECORD
