Metadata-Version: 2.4
Name: modularitypruning
Version: 1.5.0
Summary: Pruning tool to identify small subsets of network partitions that are significant from the perspective
Author-email: Ryan Gibson <ryan.alex.gibson@gmail.com>
License: MIT
Classifier: Development Status :: 5 - Production/Stable
Classifier: Topic :: Scientific/Engineering :: Information Analysis
Classifier: Programming Language :: Python :: 3
Classifier: Programming Language :: Python :: 3.8
Classifier: Programming Language :: Python :: 3.9
Classifier: Programming Language :: Python :: 3.10
Classifier: Programming Language :: Python :: 3.11
Classifier: Programming Language :: Python :: 3.12
Classifier: Programming Language :: Python :: 3.13
Classifier: Programming Language :: Python :: 3.14
Classifier: Programming Language :: Python :: 3 :: Only
Classifier: License :: OSI Approved :: MIT License
Requires-Python: >=3.8
License-File: LICENSE
Requires-Dist: leidenalg
Requires-Dist: matplotlib
Requires-Dist: numpy
Requires-Dist: psutil
Requires-Dist: igraph
Requires-Dist: scikit-learn
Requires-Dist: scipy>=1.7
Requires-Dist: seaborn
Requires-Dist: tqdm
Dynamic: license-file
